yaml2pydantic/__init__.py
yaml2pydantic/py.typed
yaml2pydantic/components/__init__.py
yaml2pydantic/core/__init__.py
yaml2pydantic/core/factory.py
yaml2pydantic/core/loader.py
yaml2pydantic/core/registry.py
yaml2pydantic/core/serializers.py
yaml2pydantic/core/type_registry.py
yaml2pydantic/core/validators.py
yaml2pydantic-0.1.0.dist-info/METADATA
yaml2pydantic-0.1.0.dist-info/WHEEL
yaml2pydantic-0.1.0.dist-info/top_level.txt
yaml2pydantic-0.1.0.dist-info/RECORD
