Metadata-Version: 2.4
Name: yaml2pydantic
Version: 0.1.0
Summary: Convert YAML schemas to Pydantic models
Requires-Python: >=3.11
Requires-Dist: pydantic>=2.0.0
Requires-Dist: pyyaml>=6.0.0
Provides-Extra: dev
Requires-Dist: ipdb>=0.13.0; extra == "dev"
Requires-Dist: rich>=13.0.0; extra == "dev"
Requires-Dist: pytest>=7.0.0; extra == "dev"
Requires-Dist: pytest-cov>=6.1.0; extra == "dev"
Requires-Dist: ruff>=0.2.0; extra == "dev"
Requires-Dist: black>=23.0.0; extra == "dev"
Requires-Dist: isort>=5.0.0; extra == "dev"
Requires-Dist: mypy>=1.0.0; extra == "dev"
Requires-Dist: types-PyYAML>=6.0.0; extra == "dev"
Requires-Dist: sphinx>=7.0.0; extra == "dev"
Requires-Dist: furo>=2023.9.10; extra == "dev"
Requires-Dist: sphinx-autodoc-typehints>=1.25.0; extra == "dev"
Requires-Dist: myst-parser>=2.0.0; extra == "dev"
Requires-Dist: sphinx-copybutton>=0.5.2; extra == "dev"
Requires-Dist: sphinx-design>=0.5.0; extra == "dev"
Requires-Dist: safety>=2.0.0; extra == "dev"
Requires-Dist: bandit>=1.7.0; extra == "dev"
Requires-Dist: trufflehog>=2.2.1; extra == "dev"
Requires-Dist: python-semantic-release>=8.0.0; extra == "dev"
Requires-Dist: toml>=0.10.2; extra == "dev"
Requires-Dist: packaging>=24.0; extra == "dev"
Requires-Dist: build>=0.11.0; extra == "dev"
Requires-Dist: twine>=5.0.0; extra == "dev"
